[
    {
        "timestamp": "2025-09-09T01:09:29.922822+00:00",
        "records": [
            {
                "observable": "A",
                "state": [
                    {
                        "name": "build number",
                        "value": 284
                    },
                    {
                        "name": "configuration",
                        "value": "Release"
                    },
                    {
                        "name": "errors",
                        "value": 5010
                    },
                    {
                        "name": "warnings",
                        "value": 290
                    }
                ]
            }
        ]
    },
    {
        "timestamp": "2025-09-09T01:09:36.547123+00:00",
        "records": [
            {
                "observable": "A",
                "state": [
                    {
                        "name": "build number",
                        "value": 284
                    },
                    {
                        "name": "configuration",
                        "value": "Release"
                    },
                    {
                        "name": "errors",
                        "value": 5010
                    },
                    {
                        "name": "warnings",
                        "value": 290
                    }
                ]
            }
        ]
    },
    {
        "timestamp": "2025-09-09T01:09:37.066893+00:00",
        "records": [
            {
                "observable": "A",
                "state": [
                    {
                        "name": "build number",
                        "value": 284
                    },
                    {
                        "name": "configuration",
                        "value": "Release"
                    },
                    {
                        "name": "errors",
                        "value": 5010
                    },
                    {
                        "name": "warnings",
                        "value": 290
                    }
                ]
            }
        ]
    },
    {
        "timestamp": "2025-09-09T01:10:11.659365+00:00",
        "records": [
            {
                "observable": "A",
                "state": [
                    {
                        "name": "build number",
                        "value": 284
                    },
                    {
                        "name": "configuration",
                        "value": "Release"
                    },
                    {
                        "name": "errors",
                        "value": 5010
                    },
                    {
                        "name": "warnings",
                        "value": 290
                    }
                ]
            },
            {
                "observable": "B",
                "state": [
                    {
                        "name": "stamina",
                        "value": 301
                    },
                    {
                        "name": "HP",
                        "value": 2420
                    },
                    {
                        "name": "Exp",
                        "value": 9
                    }
                ]
            }
        ]
    }
]